MedRxNorm/MedRxNorm.py
MedRxNorm/__init__.py
MedRxNorm/data/abbreviations.json
MedRxNorm-0.1.4.dist-info/LICENSE
MedRxNorm-0.1.4.dist-info/METADATA
MedRxNorm-0.1.4.dist-info/WHEEL
MedRxNorm-0.1.4.dist-info/top_level.txt
MedRxNorm-0.1.4.dist-info/RECORD
