Metadata-Version: 2.1
Name: MedRxNorm
Version: 0.1.4
Summary: Python module for normalizing medical prescriptions
Home-page: UNKNOWN
Author: Aaron Goyzueta
Author-email: aarongoyzueta@gmail.com
License: UNKNOWN
Project-URL: GitHub Link, https://github.com/AaronGoyzueta/MedRxNorm
Platform: UNKNOWN
Requires-Dist: pynini
Requires-Dist: num2words
Requires-Dist: textblob
Requires-Dist: text2digits
